jr_connection/__init__.py
jr_connection/first_run.py
jr_connection/other_constants.py
jr_connection/classes/__init__.py
jr_connection/classes/connection_class.py
jr_connection/classes/data_handler_class.py
jr_connection/classes/dbconfig_class.py
jr_connection-0.1.3.dist-info/LICENSE
jr_connection-0.1.3.dist-info/METADATA
jr_connection-0.1.3.dist-info/WHEEL
jr_connection-0.1.3.dist-info/entry_points.txt
jr_connection-0.1.3.dist-info/top_level.txt
jr_connection-0.1.3.dist-info/RECORD
